ste_github_tools/github_tools.py
ste_github_tools-0.0.4.dist-info/METADATA
ste_github_tools-0.0.4.dist-info/WHEEL
ste_github_tools-0.0.4.dist-info/top_level.txt
ste_github_tools-0.0.4.dist-info/RECORD
