Metadata-Version: 2.1
Name: ste-github-tools
Version: 0.0.4
Summary: Use github api to perform tasks, e.g. check pr status, create milestone..
Author: Svein Tore Eikeskog
Author-email: st@eikeskog.com
